[
    {
        "kodeBarang": "FOC0D0000480090YA000RO",
        "namaBarang": "DAIMARU OPP 48 X 90Y TRANSP",
        "isiPerBox": "72",
        "sisaStok": "0"
    },
    {
        "kodeBarang": "FOT0D0000480090YA000RO",
        "namaBarang": "DAIMARU OPP 48 X 90Y TAN",
        "isiPerBox": "72",
        "sisaStok": "0"
    },
    {
        "kodeBarang": "FOC0D0000480090YA000VK",
        "namaBarang": "DAIMARU OPP 48 X 90Y CLEAR (VK13)",
        "isiPerBox": "36",
        "sisaStok": "0"
    },
    {
        "kodeBarang": "FOM0D0000480090YA000RO",
        "namaBarang": "DAIMARU OPP 48 X 90Y MERAH",
        "isiPerBox": "72",
        "sisaStok": "0"
    },
    {
        "kodeBarang": "FOK0D0000480090YA000RO",
        "namaBarang": "DAIMARU OPP 48 X 90Y KUNING",
        "isiPerBox": "72",
        "sisaStok": "0"
    },
    {
        "kodeBarang": "FOG0D0000480090YA000RO",
        "namaBarang": "DAIMARU OPP 48 X 90Y HIJAU",
        "isiPerBox": "72",
        "sisaStok": "0"
    },
    {
        "kodeBarang": "FOB0D0000480090YA000RO",
        "namaBarang": "DAIMARU OPP 48 X 90Y BIRU",
        "isiPerBox": "72",
        "sisaStok": "0"
    },
    {
        "kodeBarang": "FOO0D0000480090YA000RO",
        "namaBarang": "DAIMARU OPP 48 X 90Y ORANGE",
        "isiPerBox": "72",
        "sisaStok": "0"
    },
    {
        "kodeBarang": "FOW0D0000480090YA000RO",
        "namaBarang": "DAIMARU OPP 48 X 90Y PUTIH",
        "isiPerBox": "72",
        "sisaStok": "0"
    },
    {
        "kodeBarang": "FOC0D0000720100MA000RO",
        "namaBarang": "DAIMARU OPP 72 X 100M TRANSP",
        "isiPerBox": "32",
        "sisaStok": "0"
    },
    {
        "kodeBarang": "FOT0D0000720100MA000RO",
        "namaBarang": "DAIMARU OPP 72 X 100M TAN",
        "isiPerBox": "32",
        "sisaStok": "0"
    },
    {
        "kodeBarang": "FOC0D0000480500MA000RO",
        "namaBarang": "DAIMARU OPP 48 X 500M TRANSP",
        "isiPerBox": "12",
        "sisaStok": "0"
    },
    {
        "kodeBarang": "FOC0E0000450055YA000RO",
        "namaBarang": "EKATAPE OPP BIRU 45 X 55Y TRANS",
        "isiPerBox": "72",
        "sisaStok": "0"
    },
    {
        "kodeBarang": "FOT0E0000450055YA000RO",
        "namaBarang": "EKATAPE OPP BIRU 45 X 55Y TAN",
        "isiPerBox": "72",
        "sisaStok": "0"
    },
    {
        "kodeBarang": "FOC0E0000450065YA000RO",
        "namaBarang": "EKATAPE OPP HIJAU 45 X 65Y TRANS",
        "isiPerBox": "72",
        "sisaStok": "0"
    },
    {
        "kodeBarang": "FOT0E0000450065YA000RO",
        "namaBarang": "EKATAPE OPP HIJAU 45 X 65Y TAN",
        "isiPerBox": "72",
        "sisaStok": "0"
    },
    {
        "kodeBarang": "FOC0E0000450085YA000RO",
        "namaBarang": "EKATAPE OPP MERAH 45 X 85Y TRANS",
        "isiPerBox": "72",
        "sisaStok": "0"
    },
    {
        "kodeBarang": "FOT0E0000450085YA000RO",
        "namaBarang": "EKATAPE OPP MERAH 45 X 85Y TAN",
        "isiPerBox": "72",
        "sisaStok": "0"
    },
    {
        "kodeBarang": "FOC0S0000450040YC000RO",
        "namaBarang": "SUPERFIX OPP 45 X 40Y TRANSP",
        "isiPerBox": "72",
        "sisaStok": "0"
    },
    {
        "kodeBarang": "FOT0S0000450040YC000RO",
        "namaBarang": "SUPERFIX OPP 45 X 40Y TAN",
        "isiPerBox": "72",
        "sisaStok": "0"
    },
    {
        "kodeBarang": "FPW000000480100MF0001W",
        "namaBarang": "OPP PRINTED 48 X 100M FRAGILE",
        "isiPerBox": "48",
        "sisaStok": "0"
    },
    {
        "kodeBarang": "FPW000000480100MH0001W",
        "namaBarang": "OPP PRINTED 48 X 100M JANGAN DIBANTING",
        "isiPerBox": "48",
        "sisaStok": "0"
    },
    {
        "kodeBarang": "FPW0O0000180050MH0081B",
        "namaBarang": "OPP PRINTED 18 X 50M PAID",
        "isiPerBox": "128",
        "sisaStok": "0"
    },
    {
        "kodeBarang": "FZN0D0000120010YE000RO",
        "namaBarang": "DAIMARU SAT MINISELOTIP 12 X 10Y",
        "isiPerBox": "1200",
        "sisaStok": "0"
    },
    {
        "kodeBarang": "FZN0D0000120025YE000RO",
        "namaBarang": "DAIMARU SAT MINISELOTIP 12 X 25Y",
        "isiPerBox": "960",
        "sisaStok": "0"
    },
    {
        "kodeBarang": "FZ00DI100120072YC000RO",
        "namaBarang": "DAIMARU SAT INDUSTRI 12 X 72Y",
        "isiPerBox": "288",
        "sisaStok": "0"
    },
    {
        "kodeBarang": "FZ00DI100240072YC000RO",
        "namaBarang": "DAIMARU SAT INDUSTRI 24 X 72Y",
        "isiPerBox": "144",
        "sisaStok": "0"
    },
    {
        "kodeBarang": "FZ00DP100120072YB000RO",
        "namaBarang": "DAIMARU SAT PREMIUM 12 X 72Y",
        "isiPerBox": "288",
        "sisaStok": "0"
    },
    {
        "kodeBarang": "FZ00DP100240072YB000RO",
        "namaBarang": "DAIMARU SAT PREMIUM 24 X 72Y",
        "isiPerBox": "144",
        "sisaStok": "0"
    },
    {
        "kodeBarang": "FCH0CA000240005M0000RO",
        "namaBarang": "DAIICHI CLT 24 X 5M HITAM",
        "isiPerBox": "120",
        "sisaStok": "0"
    },
    {
        "kodeBarang": "FCH0CA000360005M0000RO",
        "namaBarang": "DAIICHI CLT 36 X 5M HITAM",
        "isiPerBox": "80",
        "sisaStok": "0"
    },
    {
        "kodeBarang": "FCH0CA000480005M0000RO",
        "namaBarang": "DAIICHI CLT 48 X 5M HITAM",
        "isiPerBox": "60",
        "sisaStok": "0"
    },
    {
        "kodeBarang": "FCH0DA000240012M0000RO",
        "namaBarang": "DAIMARU CLT 24 X 12M HITAM",
        "isiPerBox": "120",
        "sisaStok": "0"
    },
    {
        "kodeBarang": "FCH0DA000360012M0000RO",
        "namaBarang": "DAIMARU CLT 36 X 12M HITAM",
        "isiPerBox": "60",
        "sisaStok": "0"
    },
    {
        "kodeBarang": "FCH0DA000480012M0000RO",
        "namaBarang": "DAIMARU CLT 48 X 12M HITAM",
        "isiPerBox": "61",
        "sisaStok": "0"
    },
    {
        "kodeBarang": "FCM0DA000480012M0000RO",
        "namaBarang": "DAIMARU CLT 48 X 12M MERAH",
        "isiPerBox": "60",
        "sisaStok": "0"
    },
    {
        "kodeBarang": "FCK0DA000480012M0000RO",
        "namaBarang": "DAIMARU CLT 48 X 12M KUNING",
        "isiPerBox": "60",
        "sisaStok": "0"
    },
    {
        "kodeBarang": "FCG0DA000480012M0000RO",
        "namaBarang": "DAIMARU CLT 48 X 12M HIJAU",
        "isiPerBox": "60",
        "sisaStok": "0"
    },
    {
        "kodeBarang": "FCB0DA000480012M0000RO",
        "namaBarang": "DAIMARU CLT 48 X 12M BIRU",
        "isiPerBox": "60",
        "sisaStok": "0"
    },
    {
        "kodeBarang": "FCR0DA000480012M0000RO",
        "namaBarang": "DAIMARU CLT 48 X 12M CREAM",
        "isiPerBox": "60",
        "sisaStok": "0"
    },
    {
        "kodeBarang": "FCP0D0000480012M0000UM",
        "namaBarang": "DAIMARU CLT 48 X 12M PINK",
        "isiPerBox": "60",
        "sisaStok": "0"
    },
    {
        "kodeBarang": "FCH0EB100340010Y0000RO",
        "namaBarang": "EKATAPE CLT 34 X 10Y HITAM",
        "isiPerBox": "80",
        "sisaStok": "0"
    },
    {
        "kodeBarang": "FCH0EB100460010Y0000RO",
        "namaBarang": "EKATAPE CLT 46 X 10Y HITAM",
        "isiPerBox": "60",
        "sisaStok": "0"
    },
    {
        "kodeBarang": "FM00DI000120021M0000RO",
        "namaBarang": "DAIMARU MASKING 12 X 21M",
        "isiPerBox": "192",
        "sisaStok": "0"
    },
    {
        "kodeBarang": "FM00DI000240021M0000RO",
        "namaBarang": "DAIMARU MASKING 24 X 21M",
        "isiPerBox": "96",
        "sisaStok": "0"
    },
    {
        "kodeBarang": "FM00DI000480021M0000RO",
        "namaBarang": "DAIMARU MASKING 48 X 21M",
        "isiPerBox": "48",
        "sisaStok": "0"
    },
    {
        "kodeBarang": "FM00EJ000240015Y0000RO",
        "namaBarang": "EKATAPE MASKING TAPE 24 X 15Y",
        "isiPerBox": "36",
        "sisaStok": "0"
    },
    {
        "kodeBarang": "FM00EJ000480015Y0000RO",
        "namaBarang": "EKATAPE MASKING TAPE 48 X 15Y",
        "isiPerBox": "24",
        "sisaStok": "0"
    },
    {
        "kodeBarang": "FM00EJ000240020M0000RO",
        "namaBarang": "EKATAPE MASKING TAPE 24 X 20M",
        "isiPerBox": "36",
        "sisaStok": "0"
    },
    {
        "kodeBarang": "FM00EJ000480020M0000RO",
        "namaBarang": "EKATAPE MASKING TAPE 48 X 20M",
        "isiPerBox": "24",
        "sisaStok": "0"
    },
    {
        "kodeBarang": "FM00SM200240020YQ200UM",
        "namaBarang": "SUPERFIX MASKING 24 X 20Y",
        "isiPerBox": "96",
        "sisaStok": "0"
    },
    {
        "kodeBarang": "FD00DQ000120012YP000RO",
        "namaBarang": "DAIMARU DOUBLE TP 12 X 12Y",
        "isiPerBox": "240",
        "sisaStok": "0"
    },
    {
        "kodeBarang": "FD00DQ000240012YP000RO",
        "namaBarang": "DAIMARU DOUBLE TP 24 X 12Y",
        "isiPerBox": "120",
        "sisaStok": "0"
    },
    {
        "kodeBarang": "FD00DQ000480012YP000RO",
        "namaBarang": "DAIMARU DOUBLE TP 48 X 12Y",
        "isiPerBox": "60",
        "sisaStok": "0"
    },
    {
        "kodeBarang": "FF00D0000240005M0000RO",
        "namaBarang": "DAIMARU DOUBLE FOAM 24 X 5M",
        "isiPerBox": "96",
        "sisaStok": "0"
    },
    {
        "kodeBarang": "FF00D0000480005M0000RO",
        "namaBarang": "DAIMARU DOUBLE FOAM 48 X 5M",
        "isiPerBox": "48",
        "sisaStok": "0"
    },
    {
        "kodeBarang": "FL00DU000480040Y0000RO",
        "namaBarang": "DAIMARU ALUMINIUM FOIL 48 X 40Y",
        "isiPerBox": "24",
        "sisaStok": "0"
    },
    {
        "kodeBarang": "FEH0DX000190020MO000RO",
        "namaBarang": "DAIMARU PVC HITAM 19 X 20M",
        "isiPerBox": "120",
        "sisaStok": "0"
    },
    {
        "kodeBarang": "FS00P0005000200ML000RO",
        "namaBarang": "STRECTCH FILM 500 X 200M X 17MIC",
        "isiPerBox": "6",
        "sisaStok": "0"
    },
    {
        "kodeBarang": "FS00P0005000300ML000RO",
        "namaBarang": "STRECTCH FILM 500 X 300M X 17MIC",
        "isiPerBox": "6",
        "sisaStok": "0"
    },
    {
        "kodeBarang": "FS00P0005001500ML000RO",
        "namaBarang": "STRECTCH FILM 500 X 1500M X 17MIC",
        "isiPerBox": "1",
        "sisaStok": "0"
    },
    {
        "kodeBarang": "FI00D0003000030MT000RO",
        "namaBarang": "DAIMARU CLING WRAP 300 X 30M X 10MIC",
        "isiPerBox": "24",
        "sisaStok": "0"
    },
    {
        "kodeBarang": "FI00D0003000500MK000RO",
        "namaBarang": "DAIMARU CLING WRAP 300 X 500M X 12MIC",
        "isiPerBox": "6",
        "sisaStok": "0"
    },
    {
        "kodeBarang": "FOC0I0000480064MA001RT",
        "namaBarang": "INDOMARET OPP 48 X 64M TRANSP",
        "isiPerBox": "48",
        "sisaStok": "0"
    },
    {
        "kodeBarang": "FOT0I0000480064MA001RT",
        "namaBarang": "INDOMARET OPP 48 X 64M TAN",
        "isiPerBox": "48",
        "sisaStok": "0"
    },
    {
        "kodeBarang": "FD00I0000120011MP001IM",
        "namaBarang": "INDOMARET DOUBLE TP 12 X 11M",
        "isiPerBox": "240",
        "sisaStok": "0"
    },
    {
        "kodeBarang": "FZ000I100240066MC001IM",
        "namaBarang": "INDOMARET SAT INDUSTRI 24 X 66M",
        "isiPerBox": "144",
        "sisaStok": "0"
    },
    {
        "kodeBarang": "FZN0I0000120025YE002RT",
        "namaBarang": "INDOMARET MINISELOTIP 12 X 25Y (2 ROLL/PACK)",
        "isiPerBox": "288",
        "sisaStok": "0"
    },
    {
        "kodeBarang": "FOC000000480100MA001LR",
        "namaBarang": "LARRIST OPP 48 X 100M TRANP",
        "isiPerBox": "48",
        "sisaStok": "0"
    },
    {
        "kodeBarang": "FOT000000480100MA001LR",
        "namaBarang": "LARRIST OPP 48 X 100M TAN",
        "isiPerBox": "48",
        "sisaStok": "0"
    },
    {
        "kodeBarang": "FZ000I100120072YC000LR",
        "namaBarang": "LARISST SAT INDUSTRI 12 X 72Y",
        "isiPerBox": "288",
        "sisaStok": "0"
    },
    {
        "kodeBarang": "FZ000I100240072YC000LR",
        "namaBarang": "LARISST SAT INDUSTRI 24 X 72Y",
        "isiPerBox": "144",
        "sisaStok": "0"
    },
    {
        "kodeBarang": "FPW0O0000480100ME0011W",
        "namaBarang": "LARRIST OPP TAPE 48 X 100M FRAGILE",
        "isiPerBox": "48",
        "sisaStok": "0"
    },
    {
        "kodeBarang": "FOC0L0000480050MA001RT",
        "namaBarang": "ALFAMART OPP 48 X 50M TRANS",
        "isiPerBox": "72",
        "sisaStok": "0"
    },
    {
        "kodeBarang": "FOT0L0000480050MA001RT",
        "namaBarang": "ALFAMART OPP 48 X 50M TAN",
        "isiPerBox": "72",
        "sisaStok": "0"
    },
    {
        "kodeBarang": "FD00L0000120007MP001RT",
        "namaBarang": "ALFAMART DOUBLE TAPE 12 X 7M",
        "isiPerBox": "288",
        "sisaStok": "0"
    },
    {
        "kodeBarang": "FZC0L0000120072YC001RT",
        "namaBarang": "ALFAMART SAT INDUSTRI 12 X 72Y",
        "isiPerBox": "288",
        "sisaStok": "0"
    }
]